throwpy/ThrowPy.py
throwpy/__init__.py
throwpy-1.0.3.dist-info/licenses/LICENSE
throwpy-1.0.3.dist-info/METADATA
throwpy-1.0.3.dist-info/WHEEL
throwpy-1.0.3.dist-info/top_level.txt
throwpy-1.0.3.dist-info/RECORD
