Metadata-Version: 2.4
Name: throwpy
Version: 1.0.3
Summary: A lightweight decorator for automatic exception handling and logging in Python.
Author-email: "Giuseppe De Martino, PhD" <ThrowPy@proton.me>
License: MIT License
Project-URL: Homepage, https://github.com/demnap-work/ThrowPy
Project-URL: Issues, https://github.com/demnap-work/ThrowPy/issues
Keywords: decorator,exception,logging,error-handling,python
Classifier: Development Status :: 5 - Production/Stable
Classifier: Intended Audience :: Developers
Classifier: License :: OSI Approved :: MIT License
Classifier: Programming Language :: Python :: 3
Classifier: Programming Language :: Python :: 3.10
Classifier: Topic :: Software Development :: Libraries :: Python Modules
Requires-Python: >=3.8
License-File: LICENSE
Dynamic: license-file
